{
  "content": [
    {
      "min": 58.0,
      "max": 1070.6,
      "volume": 70140
    },
    {
      "min": 1070.6,
      "max": 2083.2,
      "volume": 51137
    },
    {
      "min": 2083.2,
      "max": 3095.8,
      "volume": 11098
    },
    {
      "min": 3095.8,
      "max": 4108.4,
      "volume": 2836
    },
    {
      "min": 4108.4,
      "max": 5121.0,
      "volume": 817
    },
    {
      "min": 5121.0,
      "max": 6133.6,
      "volume": 244
    },
    {
      "min": 6133.6,
      "max": 7146.2,
      "volume": 5900
    },
    {
      "min": 7146.2,
      "max": 8158.8,
      "volume": 12000
    },
    {
      "min": 8158.8,
      "max": 9171.4,
      "volume": 18000
    },
    {
      "min": 9171.4,
      "max": 10184.0,
      "volume": 20000
    },
    {
      "min": 10184.0,
      "max": 11196.6,
      "volume": 10000
    },
    {
      "min": 11196.6,
      "max": 12209.2,
      "volume": 4400
    },
    {
      "min": 12209.2,
      "max": 13221.8,
      "volume": 4
    },
    {
      "min": 13221.8,
      "max": 14234.4,
      "volume": 2
    },
    {
      "min": 14234.4,
      "max": 15247.0,
      "volume": 2
    },
    {
      "min": 15247.0,
      "max": 16259.6,
      "volume": 0
    },
    {
      "min": 16259.6,
      "max": 17272.2,
      "volume": 1
    },
    {
      "min": 17272.2,
      "max": 18284.8,
      "volume": 0
    },
    {
      "min": 18284.8,
      "max": 19297.4,
      "volume": 1
    },
    {
      "min": 19297.4,
      "max": 20310.0,
      "volume": 1
    }
  ]
}